otp_generator/__init__.py
otp_generator/otp.py
random_otp_generator-1.0.0.dist-info/METADATA
random_otp_generator-1.0.0.dist-info/WHEEL
random_otp_generator-1.0.0.dist-info/top_level.txt
random_otp_generator-1.0.0.dist-info/RECORD
