Metadata-Version: 2.1
Name: random-otp-generator
Version: 1.0.0
Summary: A Python package for generating OTPs.
Home-page: https://github.com/NoManNayeem/Random-OTP-Generator-API-
Author: Nayeem Islam
Author-email: islam.nayeem@outlook.com
Classifier: License :: OSI Approved :: MIT License
Classifier: Programming Language :: Python :: 3
Classifier: Programming Language :: Python :: 3.6
Classifier: Programming Language :: Python :: 3.7
Classifier: Programming Language :: Python :: 3.8
Classifier: Programming Language :: Python :: 3.9
